examples/__init__.py
examples/game_level_example.py
examples/lol/__init__.py
examples/lol/pipeline_transformer_example.py
examples/lol/data/__init__.py
examples/lol/data/subsample_lol_data.parquet
examples/lol/data/utils.py
examples/nba/__init__.py
examples/nba/cross_validation_example.py
examples/nba/feature_engineering_example.py
examples/nba/game_winner_example.py
examples/nba/predictor_transformers_example.py
examples/nba/data/__init__.py
examples/nba/data/game_player_subsample.parquet
examples/nba/data/utils.py
spforge/__init__.py
spforge/autopipeline.py
spforge/base_feature_generator.py
spforge/data_structures.py
spforge/features_generator_pipeline.py
spforge/utils.py
spforge/cross_validator/__init__.py
spforge/cross_validator/_base.py
spforge/cross_validator/cross_validator.py
spforge/distributions/__init__.py
spforge/distributions/_negative_binomial_estimator.py
spforge/distributions/_normal_distribution_predictor.py
spforge/distributions/_student_t_distribution_estimator.py
spforge/estimator/__init__.py
spforge/estimator/_conditional_estimator.py
spforge/estimator/_frequency_bucketing_classifier.py
spforge/estimator/_granularity_estimator.py
spforge/estimator/_group_by_estimator.py
spforge/estimator/_ordinal_classifier.py
spforge/estimator/_sklearn_enhancer_estimator.py
spforge/feature_generator/__init__.py
spforge/feature_generator/_base.py
spforge/feature_generator/_lag.py
spforge/feature_generator/_net_over_predicted.py
spforge/feature_generator/_regressor_feature_generator.py
spforge/feature_generator/_rolling_against_opponent.py
spforge/feature_generator/_rolling_mean_binary.py
spforge/feature_generator/_rolling_mean_days.py
spforge/feature_generator/_rolling_window.py
spforge/feature_generator/_utils.py
spforge/hyperparameter_tuning/__init__.py
spforge/hyperparameter_tuning/_default_search_spaces.py
spforge/hyperparameter_tuning/_tuner.py
spforge/performance_transformers/__init__.py
spforge/performance_transformers/_performance_manager.py
spforge-0.8.35.dist-info/licenses/LICENSE
spforge-0.8.35.dist-info/METADATA
spforge-0.8.35.dist-info/WHEEL
spforge-0.8.35.dist-info/top_level.txt
spforge-0.8.35.dist-info/RECORD
