Metadata-Version: 2.4
Name: spforge
Version: 0.8.35
Summary: A flexible framework for generating features, ratings, and building machine learning or other models for training and inference on sports data.
Author-email: Mathias Holmstrøm <mathiasholmstom@gmail.com>
License: See LICENSE file
Project-URL: Homepage, https://github.com/Hiderdk/player-performance-ratings
Project-URL: Repository, https://github.com/Hiderdk/player-performance-ratings
Keywords: sports,machine-learning,ratings,features
Classifier: Development Status :: 4 - Beta
Classifier: Intended Audience :: Developers
Classifier: Programming Language :: Python :: 3
Classifier: Programming Language :: Python :: 3.11
Classifier: Programming Language :: Python :: 3.12
Requires-Python: >=3.11
License-File: LICENSE
Requires-Dist: numpy>=1.23.4
Requires-Dist: optuna>=3.4.0
Requires-Dist: pandas<3.0.0,>=2.0.0
Requires-Dist: pendulum>=1.0.0
Requires-Dist: scikit-learn>=1.4.0
Requires-Dist: lightgbm>=4.0.0
Requires-Dist: narwhals>2.0.0
Requires-Dist: polars>=1.17.0
Requires-Dist: pyarrow>=19.0.0
Dynamic: license-file
